{
  "metadata": {
    "version": "1.0",
    "description": "墨阵碑帖现代释义数据 - 包含 80 个经典碑帖的现代文释义、创作背景、名句赏析",
    "total_steles": 80,
    "last_updated": "2024-02-20"
  },
  "steles": {
    "kai_001": {
      "title": "九成宫醴泉铭",
      "author": "欧阳询",
      "dynasty": "唐",
      "script_type": "楷书",
      "summary": "唐楷书代表作，由欧阳询书写。",
      "background": "唐贞观六年（632 年），唐太宗李世民在九成宫（今陕西麟游）避暑时，以杖导地，有泉涌出，味甘如醴，遂命魏徵撰文、欧阳询书丹刻石纪念。此碑是楷书巅峰之作，被誉为「楷书极则」。",
      "highlights": [
        "「高阁周建，长廊四起」—— 描写宫殿建筑的宏伟",
        "「其清若镜，味甘如醴」—— 描写醴泉的清澈甘甜",
        "「功高大舜，勋深伯禹」—— 歌颂唐太宗的功绩"
      ],
      "full_interpretation": "【开头】\n九成宫醴泉铭——九成宫醴泉的铭文。\n秘书监检校侍中巨鹿郡公臣魏徵奉敕撰——秘书监检校侍中巨鹿郡公臣魏徵奉皇帝命令撰写。\n率更令兼太子率更令勃海男臣欧阳询奉敕书——率更令兼太子率更令勃海男臣欧阳询奉皇帝命令书写。\n\n【描写宫殿】\n维贞观六年孟夏之月，皇帝避暑乎九成宫——贞观六年四月，皇帝到九成宫避暑。\n此则隋之仁寿宫也——这就是隋朝的仁寿宫。\n冠山抗殿，绝壑为池——山顶上建造宫殿，阻断沟壑成为池沼。\n跨水架楹，分岩耸阙——跨越水面架设楹柱，分开山岩耸立阙楼。\n高阁周建，长廊四起——高阁四周建造，长廊四面升起。\n栋宇胶葛，台榭参差——房屋交错，台榭高低不齐。\n仰视则迢递百寻，下临则峥嵘千仞——抬头看则有百寻之高，向下看则有千仞之深。\n珠璧交映，金碧相晖——珍珠美玉交相辉映，金色碧色相互辉映。\n照灼云霞，蔽亏日月——光彩照耀云霞，高大遮蔽日月。\n观其移山回涧，穷泰极侈——看它移山改涧，极其豪华奢侈。\n以人从欲，良足深尤——为了满足人的欲望，实在应该深深责备。\n\n【发现醴泉】\n至于炎景流金，无郁蒸之气——至于炎热阳光如流金，却没有闷热的气息。\n微风徐动，有凄清之凉——微风徐徐吹动，有清凉的寒意。\n信安体之佳所，诚养神之胜地——确实是安身的佳所，实在是养神的胜地。\n汉之甘泉不能尚也——汉朝的甘泉宫也不能超过它。\n皇帝爰在弱冠，经营四方——皇帝在二十岁时，就经营四方。\n逮乎立年，抚临亿兆——到了三十岁，治理亿万百姓。\n始以武功壹海内，终以文德怀远人——开始以武功统一海内，最终以文德怀柔远人。\n\n【发现醴泉经过】\n粤以四月甲申朔旬有六日己亥——在四月初一甲申日，十六日己亥日。\n上及中宫，历览台观——皇上和皇后，遍览台观。\n闲步西城之阴，踌躇高阁之下——悠闲地步行到西城北面，在高阁之下徘徊。\n俯察厥土，微觉有润——俯察那里的土地，微微觉得有湿润。\n因而以杖导之，有泉随而涌出——于是用手杖引导，有泉水随之涌出。\n乃承以石槛，引为一渠——于是用石栏承接，引导成一条水渠。\n其清若镜，味甘如醴——它清澈如镜，味道甘甜如醴酒。\n南注丹霄之右，东流度于双阙——向南注入丹霄右侧，向东流过双阙。\n\n【引用经典】\n谨案：《礼纬》云：王者刑杀当罪，赏锡当功，得礼之宜，则醴泉出于阙庭——谨按：《礼纬》说：君王刑罚杀戮与罪行相当，赏赐与功劳相当，符合礼的适宜，那么醴泉就会出现在宫阙庭院。\n《鹖冠子》曰：圣人之德，上及太清，下及太宁，中及万灵，则醴泉出——《鹖冠子》说：圣人的德行，上及天空，下及大地，中及万物，那么醴泉就会出现。\n\n【铭文】\n其词曰——铭文说：\n唯皇抚运，奄壹寰宇——只有皇帝掌握国运，统一天下。\n千载膺期，万物斯睹——千年应期，万物都被看到。\n功高大舜，勋深伯禹——功绩高于大舜，勋业深于大禹。\n绝后承前，登三迈五——绝后承前，超越三皇五帝。",
      "writing_guide": "此碑楷书法度严谨，用笔精到。临习时注意笔画的起收变化，结构的匀称，以及整体的端庄气质。建议从基本笔画开始，逐步掌握结构规律。"
    },
    "kai_002": {
      "title": "化度寺碑",
      "author": "欧阳询",
      "dynasty": "唐",
      "script_type": "楷书",
      "summary": "唐楷书代表作，由欧阳询书写。",
      "background": "化度寺碑是唐时期欧阳询的楷书代表作。唐楷书代表作，由欧阳询书写。",
      "highlights": [
        "「化度寺碑」—— 楷书经典之作",
        "「欧阳询」—— 唐著名书法家",
        "「楷书」—— 中国书法五体之一"
      ],
      "full_interpretation": "《化度寺碑》是唐时期欧阳询创作的楷书作品。\n\n唐楷书代表作，由欧阳询书写。\n\n此帖在中国书法史上占有重要地位，是学习楷书的重要范本。",
      "writing_guide": "此碑楷书法度严谨，用笔精到。临习时注意笔画的起收变化，结构的匀称，以及整体的端庄气质。建议从基本笔画开始，逐步掌握结构规律。"
    },
    "kai_004": {
      "title": "颜氏家庙碑",
      "author": "颜真卿",
      "dynasty": "唐",
      "script_type": "楷书",
      "summary": "唐楷书代表作，由颜真卿书写。",
      "background": "颜氏家庙碑是唐时期颜真卿的楷书代表作。唐楷书代表作，由颜真卿书写。",
      "highlights": [
        "「颜氏家庙碑」—— 楷书经典之作",
        "「颜真卿」—— 唐著名书法家",
        "「楷书」—— 中国书法五体之一"
      ],
      "full_interpretation": "《颜氏家庙碑》是唐时期颜真卿创作的楷书作品。\n\n唐楷书代表作，由颜真卿书写。\n\n此帖在中国书法史上占有重要地位，是学习楷书的重要范本。",
      "writing_guide": "此碑楷书法度严谨，用笔精到。临习时注意笔画的起收变化，结构的匀称，以及整体的端庄气质。建议从基本笔画开始，逐步掌握结构规律。"
    },
    "kai_005": {
      "title": "颜勤礼碑",
      "author": "颜真卿",
      "dynasty": "唐",
      "script_type": "楷书",
      "summary": "唐楷书代表作，由颜真卿书写。",
      "background": "颜勤礼碑是唐时期颜真卿的楷书代表作。唐楷书代表作，由颜真卿书写。",
      "highlights": [
        "「颜勤礼碑」—— 楷书经典之作",
        "「颜真卿」—— 唐著名书法家",
        "「楷书」—— 中国书法五体之一"
      ],
      "full_interpretation": "《颜勤礼碑》是唐时期颜真卿创作的楷书作品。\n\n唐楷书代表作，由颜真卿书写。\n\n此帖在中国书法史上占有重要地位，是学习楷书的重要范本。",
      "writing_guide": "此碑楷书法度严谨，用笔精到。临习时注意笔画的起收变化，结构的匀称，以及整体的端庄气质。建议从基本笔画开始，逐步掌握结构规律。"
    },
    "kai_006": {
      "title": "多宝塔碑",
      "author": "颜真卿",
      "dynasty": "唐",
      "script_type": "楷书",
      "summary": "唐楷书代表作，由颜真卿书写。",
      "background": "多宝塔碑是唐时期颜真卿的楷书代表作。唐楷书代表作，由颜真卿书写。",
      "highlights": [
        "「多宝塔碑」—— 楷书经典之作",
        "「颜真卿」—— 唐著名书法家",
        "「楷书」—— 中国书法五体之一"
      ],
      "full_interpretation": "《多宝塔碑》是唐时期颜真卿创作的楷书作品。\n\n唐楷书代表作，由颜真卿书写。\n\n此帖在中国书法史上占有重要地位，是学习楷书的重要范本。",
      "writing_guide": "此碑楷书法度严谨，用笔精到。临习时注意笔画的起收变化，结构的匀称，以及整体的端庄气质。建议从基本笔画开始，逐步掌握结构规律。"
    },
    "kai_007": {
      "title": "柳公权玄秘塔碑",
      "author": "柳公权",
      "dynasty": "唐",
      "script_type": "楷书",
      "summary": "唐楷书代表作，由柳公权书写。",
      "background": "柳公权玄秘塔碑是唐时期柳公权的楷书代表作。唐楷书代表作，由柳公权书写。",
      "highlights": [
        "「柳公权玄秘塔碑」—— 楷书经典之作",
        "「柳公权」—— 唐著名书法家",
        "「楷书」—— 中国书法五体之一"
      ],
      "full_interpretation": "《柳公权玄秘塔碑》是唐时期柳公权创作的楷书作品。\n\n唐楷书代表作，由柳公权书写。\n\n此帖在中国书法史上占有重要地位，是学习楷书的重要范本。",
      "writing_guide": "此碑楷书法度严谨，用笔精到。临习时注意笔画的起收变化，结构的匀称，以及整体的端庄气质。建议从基本笔画开始，逐步掌握结构规律。"
    },
    "kai_008": {
      "title": "神策军碑",
      "author": "柳公权",
      "dynasty": "唐",
      "script_type": "楷书",
      "summary": "唐楷书代表作，由柳公权书写。",
      "background": "神策军碑是唐时期柳公权的楷书代表作。唐楷书代表作，由柳公权书写。",
      "highlights": [
        "「神策军碑」—— 楷书经典之作",
        "「柳公权」—— 唐著名书法家",
        "「楷书」—— 中国书法五体之一"
      ],
      "full_interpretation": "《神策军碑》是唐时期柳公权创作的楷书作品。\n\n唐楷书代表作，由柳公权书写。\n\n此帖在中国书法史上占有重要地位，是学习楷书的重要范本。",
      "writing_guide": "此碑楷书法度严谨，用笔精到。临习时注意笔画的起收变化，结构的匀称，以及整体的端庄气质。建议从基本笔画开始，逐步掌握结构规律。"
    },
    "kai_009": {
      "title": "雁塔圣教序",
      "author": "褚遂良",
      "dynasty": "唐",
      "script_type": "楷书",
      "summary": "唐楷书代表作，由褚遂良书写。",
      "background": "雁塔圣教序是唐时期褚遂良的楷书代表作。唐楷书代表作，由褚遂良书写。",
      "highlights": [
        "「雁塔圣教序」—— 楷书经典之作",
        "「褚遂良」—— 唐著名书法家",
        "「楷书」—— 中国书法五体之一"
      ],
      "full_interpretation": "《雁塔圣教序》是唐时期褚遂良创作的楷书作品。\n\n唐楷书代表作，由褚遂良书写。\n\n此帖在中国书法史上占有重要地位，是学习楷书的重要范本。",
      "writing_guide": "此碑楷书法度严谨，用笔精到。临习时注意笔画的起收变化，结构的匀称，以及整体的端庄气质。建议从基本笔画开始，逐步掌握结构规律。"
    },
    "kai_010": {
      "title": "孟庙碑",
      "author": "虞世南",
      "dynasty": "唐",
      "script_type": "楷书",
      "summary": "唐楷书代表作，由虞世南书写。",
      "background": "孟庙碑是唐时期虞世南的楷书代表作。唐楷书代表作，由虞世南书写。",
      "highlights": [
        "「孟庙碑」—— 楷书经典之作",
        "「虞世南」—— 唐著名书法家",
        "「楷书」—— 中国书法五体之一"
      ],
      "full_interpretation": "《孟庙碑》是唐时期虞世南创作的楷书作品。\n\n唐楷书代表作，由虞世南书写。\n\n此帖在中国书法史上占有重要地位，是学习楷书的重要范本。",
      "writing_guide": "此碑楷书法度严谨，用笔精到。临习时注意笔画的起收变化，结构的匀称，以及整体的端庄气质。建议从基本笔画开始，逐步掌握结构规律。"
    },
    "kai_011": {
      "title": "董美人墓志",
      "author": "不可考",
      "dynasty": "隋",
      "script_type": "楷书",
      "summary": "隋楷书代表作，作者不可考。",
      "background": "董美人墓志是隋时期不可考的楷书代表作。隋楷书代表作，作者不可考。",
      "highlights": [
        "「董美人墓志」—— 楷书经典之作",
        "「不可考」—— 隋著名书法家",
        "「楷书」—— 中国书法五体之一"
      ],
      "full_interpretation": "《董美人墓志》是隋时期不可考创作的楷书作品。\n\n隋楷书代表作，作者不可考。\n\n此帖在中国书法史上占有重要地位，是学习楷书的重要范本。",
      "writing_guide": "此碑楷书法度严谨，用笔精到。临习时注意笔画的起收变化，结构的匀称，以及整体的端庄气质。建议从基本笔画开始，逐步掌握结构规律。"
    },
    "kai_012": {
      "title": "张猛龙碑",
      "author": "不可考",
      "dynasty": "北魏",
      "script_type": "楷书",
      "summary": "北魏楷书代表作，作者不可考。",
      "background": "张猛龙碑是北魏时期不可考的楷书代表作。北魏楷书代表作，作者不可考。",
      "highlights": [
        "「张猛龙碑」—— 楷书经典之作",
        "「不可考」—— 北魏著名书法家",
        "「楷书」—— 中国书法五体之一"
      ],
      "full_interpretation": "《张猛龙碑》是北魏时期不可考创作的楷书作品。\n\n北魏楷书代表作，作者不可考。\n\n此帖在中国书法史上占有重要地位，是学习楷书的重要范本。",
      "writing_guide": "此碑楷书法度严谨，用笔精到。临习时注意笔画的起收变化，结构的匀称，以及整体的端庄气质。建议从基本笔画开始，逐步掌握结构规律。"
    },
    "kai_013": {
      "title": "郑文公碑",
      "author": "郑道昭",
      "dynasty": "北魏",
      "script_type": "楷书",
      "summary": "北魏楷书代表作，由郑道昭书写。",
      "background": "郑文公碑是北魏时期郑道昭的楷书代表作。北魏楷书代表作，由郑道昭书写。",
      "highlights": [
        "「郑文公碑」—— 楷书经典之作",
        "「郑道昭」—— 北魏著名书法家",
        "「楷书」—— 中国书法五体之一"
      ],
      "full_interpretation": "《郑文公碑》是北魏时期郑道昭创作的楷书作品。\n\n北魏楷书代表作，由郑道昭书写。\n\n此帖在中国书法史上占有重要地位，是学习楷书的重要范本。",
      "writing_guide": "此碑楷书法度严谨，用笔精到。临习时注意笔画的起收变化，结构的匀称，以及整体的端庄气质。建议从基本笔画开始，逐步掌握结构规律。"
    },
    "kai_014": {
      "title": "龙门二十品",
      "author": "多人",
      "dynasty": "北魏",
      "script_type": "楷书",
      "summary": "北魏楷书代表作，由多人书写。",
      "background": "龙门二十品是北魏时期多人的楷书代表作。北魏楷书代表作，由多人书写。",
      "highlights": [
        "「龙门二十品」—— 楷书经典之作",
        "「多人」—— 北魏著名书法家",
        "「楷书」—— 中国书法五体之一"
      ],
      "full_interpretation": "《龙门二十品》是北魏时期多人创作的楷书作品。\n\n北魏楷书代表作，由多人书写。\n\n此帖在中国书法史上占有重要地位，是学习楷书的重要范本。",
      "writing_guide": "此碑楷书法度严谨，用笔精到。临习时注意笔画的起收变化，结构的匀称，以及整体的端庄气质。建议从基本笔画开始，逐步掌握结构规律。"
    },
    "kai_015": {
      "title": "瘗鹤铭",
      "author": "不可考",
      "dynasty": "南朝梁",
      "script_type": "楷书",
      "summary": "南朝梁楷书代表作，作者不可考。",
      "background": "瘗鹤铭是南朝梁时期不可考的楷书代表作。南朝梁楷书代表作，作者不可考。",
      "highlights": [
        "「瘗鹤铭」—— 楷书经典之作",
        "「不可考」—— 南朝梁著名书法家",
        "「楷书」—— 中国书法五体之一"
      ],
      "full_interpretation": "《瘗鹤铭》是南朝梁时期不可考创作的楷书作品。\n\n南朝梁楷书代表作，作者不可考。\n\n此帖在中国书法史上占有重要地位，是学习楷书的重要范本。",
      "writing_guide": "此碑楷书法度严谨，用笔精到。临习时注意笔画的起收变化，结构的匀称，以及整体的端庄气质。建议从基本笔画开始，逐步掌握结构规律。"
    },
    "kai_016": {
      "title": "胆巴碑",
      "author": "赵孟頫",
      "dynasty": "元",
      "script_type": "楷书",
      "summary": "元楷书代表作，由赵孟頫书写。",
      "background": "胆巴碑是元时期赵孟頫的楷书代表作。元楷书代表作，由赵孟頫书写。",
      "highlights": [
        "「胆巴碑」—— 楷书经典之作",
        "「赵孟頫」—— 元著名书法家",
        "「楷书」—— 中国书法五体之一"
      ],
      "full_interpretation": "《胆巴碑》是元时期赵孟頫创作的楷书作品。\n\n元楷书代表作，由赵孟頫书写。\n\n此帖在中国书法史上占有重要地位，是学习楷书的重要范本。",
      "writing_guide": "此碑楷书法度严谨，用笔精到。临习时注意笔画的起收变化，结构的匀称，以及整体的端庄气质。建议从基本笔画开始，逐步掌握结构规律。"
    },
    "kai_017": {
      "title": "洛神赋",
      "author": "赵孟頫",
      "dynasty": "元",
      "script_type": "楷书",
      "summary": "元楷书代表作，由赵孟頫书写。",
      "background": "洛神赋是元时期赵孟頫的楷书代表作。元楷书代表作，由赵孟頫书写。",
      "highlights": [
        "「洛神赋」—— 楷书经典之作",
        "「赵孟頫」—— 元著名书法家",
        "「楷书」—— 中国书法五体之一"
      ],
      "full_interpretation": "《洛神赋》是元时期赵孟頫创作的楷书作品。\n\n元楷书代表作，由赵孟頫书写。\n\n此帖在中国书法史上占有重要地位，是学习楷书的重要范本。",
      "writing_guide": "此碑楷书法度严谨，用笔精到。临习时注意笔画的起收变化，结构的匀称，以及整体的端庄气质。建议从基本笔画开始，逐步掌握结构规律。"
    },
    "kai_019": {
      "title": "小楷道德经",
      "author": "文徵明",
      "dynasty": "明",
      "script_type": "楷书",
      "summary": "明楷书代表作，由文徵明书写。",
      "background": "小楷道德经是明时期文徵明的楷书代表作。明楷书代表作，由文徵明书写。",
      "highlights": [
        "「小楷道德经」—— 楷书经典之作",
        "「文徵明」—— 明著名书法家",
        "「楷书」—— 中国书法五体之一"
      ],
      "full_interpretation": "《小楷道德经》是明时期文徵明创作的楷书作品。\n\n明楷书代表作，由文徵明书写。\n\n此帖在中国书法史上占有重要地位，是学习楷书的重要范本。",
      "writing_guide": "此碑楷书法度严谨，用笔精到。临习时注意笔画的起收变化，结构的匀称，以及整体的端庄气质。建议从基本笔画开始，逐步掌握结构规律。"
    },
    "kai_020": {
      "title": "灵飞经",
      "author": "钟绍京",
      "dynasty": "唐",
      "script_type": "楷书",
      "summary": "唐楷书代表作，由钟绍京书写。",
      "background": "灵飞经是唐时期钟绍京的楷书代表作。唐楷书代表作，由钟绍京书写。",
      "highlights": [
        "「灵飞经」—— 楷书经典之作",
        "「钟绍京」—— 唐著名书法家",
        "「楷书」—— 中国书法五体之一"
      ],
      "full_interpretation": "《灵飞经》是唐时期钟绍京创作的楷书作品。\n\n唐楷书代表作，由钟绍京书写。\n\n此帖在中国书法史上占有重要地位，是学习楷书的重要范本。",
      "writing_guide": "此碑楷书法度严谨，用笔精到。临习时注意笔画的起收变化，结构的匀称，以及整体的端庄气质。建议从基本笔画开始，逐步掌握结构规律。"
    },
    "kai_021": {
      "title": "前后赤壁赋",
      "author": "文徵明",
      "dynasty": "明",
      "script_type": "楷书",
      "summary": "明·文徵明小楷书苏轼《前后赤壁赋》，两赋相距二十五年，清劲苍润，一笔不苟。",
      "background": "前后赤壁赋是明时期文徵明的楷书代表作。明·文徵明小楷书苏轼《前后赤壁赋》，两赋相距二十五年，清劲苍润，一笔不苟。",
      "highlights": [
        "「前后赤壁赋」—— 楷书经典之作",
        "「文徵明」—— 明著名书法家",
        "「楷书」—— 中国书法五体之一"
      ],
      "full_interpretation": "《前后赤壁赋》是明时期文徵明创作的楷书作品。\n\n明·文徵明小楷书苏轼《前后赤壁赋》，两赋相距二十五年，清劲苍润，一笔不苟。\n\n此帖在中国书法史上占有重要地位，是学习楷书的重要范本。",
      "writing_guide": "此碑楷书法度严谨，用笔精到。临习时注意笔画的起收变化，结构的匀称，以及整体的端庄气质。建议从基本笔画开始，逐步掌握结构规律。"
    },
    "li_001": {
      "title": "曹全碑",
      "author": "不可考",
      "dynasty": "东汉",
      "script_type": "隶书",
      "summary": "东汉隶书代表作，作者不可考。",
      "background": "曹全碑是东汉时期不可考的隶书代表作。东汉隶书代表作，作者不可考。",
      "highlights": [
        "「曹全碑」—— 隶书经典之作",
        "「不可考」—— 东汉著名书法家",
        "「隶书」—— 中国书法五体之一"
      ],
      "full_interpretation": "《曹全碑》是东汉时期不可考创作的隶书作品。\n\n东汉隶书代表作，作者不可考。\n\n此帖在中国书法史上占有重要地位，是学习隶书的重要范本。",
      "writing_guide": "此隶书古朴厚重，用笔沉稳。临习时注意蚕头燕尾的特点，结构的扁平，以及整体的古朴气质。建议从基本笔画开始，逐步掌握结构规律。"
    },
    "li_002": {
      "title": "礼器碑",
      "author": "不可考",
      "dynasty": "东汉",
      "script_type": "隶书",
      "summary": "东汉隶书代表作，作者不可考。",
      "background": "礼器碑是东汉时期不可考的隶书代表作。东汉隶书代表作，作者不可考。",
      "highlights": [
        "「礼器碑」—— 隶书经典之作",
        "「不可考」—— 东汉著名书法家",
        "「隶书」—— 中国书法五体之一"
      ],
      "full_interpretation": "《礼器碑》是东汉时期不可考创作的隶书作品。\n\n东汉隶书代表作，作者不可考。\n\n此帖在中国书法史上占有重要地位，是学习隶书的重要范本。",
      "writing_guide": "此隶书古朴厚重，用笔沉稳。临习时注意蚕头燕尾的特点，结构的扁平，以及整体的古朴气质。建议从基本笔画开始，逐步掌握结构规律。"
    },
    "li_003": {
      "title": "乙瑛碑",
      "author": "不可考",
      "dynasty": "东汉",
      "script_type": "隶书",
      "summary": "东汉隶书代表作，作者不可考。",
      "background": "乙瑛碑是东汉时期不可考的隶书代表作。东汉隶书代表作，作者不可考。",
      "highlights": [
        "「乙瑛碑」—— 隶书经典之作",
        "「不可考」—— 东汉著名书法家",
        "「隶书」—— 中国书法五体之一"
      ],
      "full_interpretation": "《乙瑛碑》是东汉时期不可考创作的隶书作品。\n\n东汉隶书代表作，作者不可考。\n\n此帖在中国书法史上占有重要地位，是学习隶书的重要范本。",
      "writing_guide": "此隶书古朴厚重，用笔沉稳。临习时注意蚕头燕尾的特点，结构的扁平，以及整体的古朴气质。建议从基本笔画开始，逐步掌握结构规律。"
    },
    "li_004": {
      "title": "张迁碑",
      "author": "不可考",
      "dynasty": "东汉",
      "script_type": "隶书",
      "summary": "东汉隶书代表作，作者不可考。",
      "background": "张迁碑是东汉时期不可考的隶书代表作。东汉隶书代表作，作者不可考。",
      "highlights": [
        "「张迁碑」—— 隶书经典之作",
        "「不可考」—— 东汉著名书法家",
        "「隶书」—— 中国书法五体之一"
      ],
      "full_interpretation": "《张迁碑》是东汉时期不可考创作的隶书作品。\n\n东汉隶书代表作，作者不可考。\n\n此帖在中国书法史上占有重要地位，是学习隶书的重要范本。",
      "writing_guide": "此隶书古朴厚重，用笔沉稳。临习时注意蚕头燕尾的特点，结构的扁平，以及整体的古朴气质。建议从基本笔画开始，逐步掌握结构规律。"
    },
    "li_005": {
      "title": "石门颂",
      "author": "不可考",
      "dynasty": "东汉",
      "script_type": "隶书",
      "summary": "东汉隶书代表作，作者不可考。",
      "background": "石门颂是东汉时期不可考的隶书代表作。东汉隶书代表作，作者不可考。",
      "highlights": [
        "「石门颂」—— 隶书经典之作",
        "「不可考」—— 东汉著名书法家",
        "「隶书」—— 中国书法五体之一"
      ],
      "full_interpretation": "《石门颂》是东汉时期不可考创作的隶书作品。\n\n东汉隶书代表作，作者不可考。\n\n此帖在中国书法史上占有重要地位，是学习隶书的重要范本。",
      "writing_guide": "此隶书古朴厚重，用笔沉稳。临习时注意蚕头燕尾的特点，结构的扁平，以及整体的古朴气质。建议从基本笔画开始，逐步掌握结构规律。"
    },
    "li_006": {
      "title": "华山碑",
      "author": "不可考",
      "dynasty": "东汉",
      "script_type": "隶书",
      "summary": "东汉隶书代表作，作者不可考。",
      "background": "华山碑是东汉时期不可考的隶书代表作。东汉隶书代表作，作者不可考。",
      "highlights": [
        "「华山碑」—— 隶书经典之作",
        "「不可考」—— 东汉著名书法家",
        "「隶书」—— 中国书法五体之一"
      ],
      "full_interpretation": "《华山碑》是东汉时期不可考创作的隶书作品。\n\n东汉隶书代表作，作者不可考。\n\n此帖在中国书法史上占有重要地位，是学习隶书的重要范本。",
      "writing_guide": "此隶书古朴厚重，用笔沉稳。临习时注意蚕头燕尾的特点，结构的扁平，以及整体的古朴气质。建议从基本笔画开始，逐步掌握结构规律。"
    },
    "li_007": {
      "title": "史晨碑",
      "author": "不可考",
      "dynasty": "东汉",
      "script_type": "隶书",
      "summary": "东汉隶书代表作，作者不可考。",
      "background": "史晨碑是东汉时期不可考的隶书代表作。东汉隶书代表作，作者不可考。",
      "highlights": [
        "「史晨碑」—— 隶书经典之作",
        "「不可考」—— 东汉著名书法家",
        "「隶书」—— 中国书法五体之一"
      ],
      "full_interpretation": "《史晨碑》是东汉时期不可考创作的隶书作品。\n\n东汉隶书代表作，作者不可考。\n\n此帖在中国书法史上占有重要地位，是学习隶书的重要范本。",
      "writing_guide": "此隶书古朴厚重，用笔沉稳。临习时注意蚕头燕尾的特点，结构的扁平，以及整体的古朴气质。建议从基本笔画开始，逐步掌握结构规律。"
    },
    "li_008": {
      "title": "衡方碑",
      "author": "不可考",
      "dynasty": "东汉",
      "script_type": "隶书",
      "summary": "东汉隶书代表作，作者不可考。",
      "background": "衡方碑是东汉时期不可考的隶书代表作。东汉隶书代表作，作者不可考。",
      "highlights": [
        "「衡方碑」—— 隶书经典之作",
        "「不可考」—— 东汉著名书法家",
        "「隶书」—— 中国书法五体之一"
      ],
      "full_interpretation": "《衡方碑》是东汉时期不可考创作的隶书作品。\n\n东汉隶书代表作，作者不可考。\n\n此帖在中国书法史上占有重要地位，是学习隶书的重要范本。",
      "writing_guide": "此隶书古朴厚重，用笔沉稳。临习时注意蚕头燕尾的特点，结构的扁平，以及整体的古朴气质。建议从基本笔画开始，逐步掌握结构规律。"
    },
    "li_009": {
      "title": "鲜于璜碑",
      "author": "不可考",
      "dynasty": "东汉",
      "script_type": "隶书",
      "summary": "东汉隶书代表作，作者不可考。",
      "background": "鲜于璜碑是东汉时期不可考的隶书代表作。东汉隶书代表作，作者不可考。",
      "highlights": [
        "「鲜于璜碑」—— 隶书经典之作",
        "「不可考」—— 东汉著名书法家",
        "「隶书」—— 中国书法五体之一"
      ],
      "full_interpretation": "《鲜于璜碑》是东汉时期不可考创作的隶书作品。\n\n东汉隶书代表作，作者不可考。\n\n此帖在中国书法史上占有重要地位，是学习隶书的重要范本。",
      "writing_guide": "此隶书古朴厚重，用笔沉稳。临习时注意蚕头燕尾的特点，结构的扁平，以及整体的古朴气质。建议从基本笔画开始，逐步掌握结构规律。"
    },
    "li_010": {
      "title": "孔宙碑",
      "author": "不可考",
      "dynasty": "东汉",
      "script_type": "隶书",
      "summary": "东汉隶书代表作，作者不可考。",
      "background": "孔宙碑是东汉时期不可考的隶书代表作。东汉隶书代表作，作者不可考。",
      "highlights": [
        "「孔宙碑」—— 隶书经典之作",
        "「不可考」—— 东汉著名书法家",
        "「隶书」—— 中国书法五体之一"
      ],
      "full_interpretation": "《孔宙碑》是东汉时期不可考创作的隶书作品。\n\n东汉隶书代表作，作者不可考。\n\n此帖在中国书法史上占有重要地位，是学习隶书的重要范本。",
      "writing_guide": "此隶书古朴厚重，用笔沉稳。临习时注意蚕头燕尾的特点，结构的扁平，以及整体的古朴气质。建议从基本笔画开始，逐步掌握结构规律。"
    },
    "li_011": {
      "title": "衡方碑",
      "author": "不可考",
      "dynasty": "东汉",
      "script_type": "隶书",
      "summary": "东汉隶书代表作，作者不可考。",
      "background": "衡方碑是东汉时期不可考的隶书代表作。东汉隶书代表作，作者不可考。",
      "highlights": [
        "「衡方碑」—— 隶书经典之作",
        "「不可考」—— 东汉著名书法家",
        "「隶书」—— 中国书法五体之一"
      ],
      "full_interpretation": "《衡方碑》是东汉时期不可考创作的隶书作品。\n\n东汉隶书代表作，作者不可考。\n\n此帖在中国书法史上占有重要地位，是学习隶书的重要范本。",
      "writing_guide": "此隶书古朴厚重，用笔沉稳。临习时注意蚕头燕尾的特点，结构的扁平，以及整体的古朴气质。建议从基本笔画开始，逐步掌握结构规律。"
    },
    "li_012": {
      "title": "鲁峻碑",
      "author": "不可考",
      "dynasty": "东汉",
      "script_type": "隶书",
      "summary": "东汉隶书代表作，作者不可考。",
      "background": "鲁峻碑是东汉时期不可考的隶书代表作。东汉隶书代表作，作者不可考。",
      "highlights": [
        "「鲁峻碑」—— 隶书经典之作",
        "「不可考」—— 东汉著名书法家",
        "「隶书」—— 中国书法五体之一"
      ],
      "full_interpretation": "《鲁峻碑》是东汉时期不可考创作的隶书作品。\n\n东汉隶书代表作，作者不可考。\n\n此帖在中国书法史上占有重要地位，是学习隶书的重要范本。",
      "writing_guide": "此隶书古朴厚重，用笔沉稳。临习时注意蚕头燕尾的特点，结构的扁平，以及整体的古朴气质。建议从基本笔画开始，逐步掌握结构规律。"
    },
    "li_013": {
      "title": "陡山城隍庙碑",
      "author": "不可考",
      "dynasty": "东汉",
      "script_type": "隶书",
      "summary": "东汉隶书代表作，作者不可考。",
      "background": "陡山城隍庙碑是东汉时期不可考的隶书代表作。东汉隶书代表作，作者不可考。",
      "highlights": [
        "「陡山城隍庙碑」—— 隶书经典之作",
        "「不可考」—— 东汉著名书法家",
        "「隶书」—— 中国书法五体之一"
      ],
      "full_interpretation": "《陡山城隍庙碑》是东汉时期不可考创作的隶书作品。\n\n东汉隶书代表作，作者不可考。\n\n此帖在中国书法史上占有重要地位，是学习隶书的重要范本。",
      "writing_guide": "此隶书古朴厚重，用笔沉稳。临习时注意蚕头燕尾的特点，结构的扁平，以及整体的古朴气质。建议从基本笔画开始，逐步掌握结构规律。"
    },
    "li_014": {
      "title": "封龙山颂",
      "author": "不可考",
      "dynasty": "东汉",
      "script_type": "隶书",
      "summary": "东汉隶书代表作，作者不可考。",
      "background": "封龙山颂是东汉时期不可考的隶书代表作。东汉隶书代表作，作者不可考。",
      "highlights": [
        "「封龙山颂」—— 隶书经典之作",
        "「不可考」—— 东汉著名书法家",
        "「隶书」—— 中国书法五体之一"
      ],
      "full_interpretation": "《封龙山颂》是东汉时期不可考创作的隶书作品。\n\n东汉隶书代表作，作者不可考。\n\n此帖在中国书法史上占有重要地位，是学习隶书的重要范本。",
      "writing_guide": "此隶书古朴厚重，用笔沉稳。临习时注意蚕头燕尾的特点，结构的扁平，以及整体的古朴气质。建议从基本笔画开始，逐步掌握结构规律。"
    },
    "li_015": {
      "title": "五凤刻石",
      "author": "不可考",
      "dynasty": "西汉",
      "script_type": "隶书",
      "summary": "西汉隶书代表作，作者不可考。",
      "background": "五凤刻石是西汉时期不可考的隶书代表作。西汉隶书代表作，作者不可考。",
      "highlights": [
        "「五凤刻石」—— 隶书经典之作",
        "「不可考」—— 西汉著名书法家",
        "「隶书」—— 中国书法五体之一"
      ],
      "full_interpretation": "《五凤刻石》是西汉时期不可考创作的隶书作品。\n\n西汉隶书代表作，作者不可考。\n\n此帖在中国书法史上占有重要地位，是学习隶书的重要范本。",
      "writing_guide": "此隶书古朴厚重，用笔沉稳。临习时注意蚕头燕尾的特点，结构的扁平，以及整体的古朴气质。建议从基本笔画开始，逐步掌握结构规律。"
    },
    "li_016": {
      "title": "莱子侯刻石",
      "author": "不可考",
      "dynasty": "西汉",
      "script_type": "隶书",
      "summary": "西汉隶书代表作，作者不可考。",
      "background": "莱子侯刻石是西汉时期不可考的隶书代表作。西汉隶书代表作，作者不可考。",
      "highlights": [
        "「莱子侯刻石」—— 隶书经典之作",
        "「不可考」—— 西汉著名书法家",
        "「隶书」—— 中国书法五体之一"
      ],
      "full_interpretation": "《莱子侯刻石》是西汉时期不可考创作的隶书作品。\n\n西汉隶书代表作，作者不可考。\n\n此帖在中国书法史上占有重要地位，是学习隶书的重要范本。",
      "writing_guide": "此隶书古朴厚重，用笔沉稳。临习时注意蚕头燕尾的特点，结构的扁平，以及整体的古朴气质。建议从基本笔画开始，逐步掌握结构规律。"
    },
    "li_017": {
      "title": "群臣上酬刻石",
      "author": "不可考",
      "dynasty": "西汉",
      "script_type": "隶书",
      "summary": "西汉隶书代表作，作者不可考。",
      "background": "群臣上酬刻石是西汉时期不可考的隶书代表作。西汉隶书代表作，作者不可考。",
      "highlights": [
        "「群臣上酬刻石」—— 隶书经典之作",
        "「不可考」—— 西汉著名书法家",
        "「隶书」—— 中国书法五体之一"
      ],
      "full_interpretation": "《群臣上酬刻石》是西汉时期不可考创作的隶书作品。\n\n西汉隶书代表作，作者不可考。\n\n此帖在中国书法史上占有重要地位，是学习隶书的重要范本。",
      "writing_guide": "此隶书古朴厚重，用笔沉稳。临习时注意蚕头燕尾的特点，结构的扁平，以及整体的古朴气质。建议从基本笔画开始，逐步掌握结构规律。"
    },
    "li_180": {
      "title": "邓石如隶书",
      "author": "邓石如",
      "dynasty": "清",
      "script_type": "隶书",
      "summary": "清隶书代表作，由邓石如书写。",
      "background": "邓石如隶书是清时期邓石如的隶书代表作。清隶书代表作，由邓石如书写。",
      "highlights": [
        "「邓石如隶书」—— 隶书经典之作",
        "「邓石如」—— 清著名书法家",
        "「隶书」—— 中国书法五体之一"
      ],
      "full_interpretation": "《邓石如隶书》是清时期邓石如创作的隶书作品。\n\n清隶书代表作，由邓石如书写。\n\n此帖在中国书法史上占有重要地位，是学习隶书的重要范本。",
      "writing_guide": "此隶书古朴厚重，用笔沉稳。临习时注意蚕头燕尾的特点，结构的扁平，以及整体的古朴气质。建议从基本笔画开始，逐步掌握结构规律。"
    },
    "li_019": {
      "title": "伊秉绶隶书",
      "author": "伊秉绶",
      "dynasty": "清",
      "script_type": "隶书",
      "summary": "清隶书代表作，由伊秉绶书写。",
      "background": "伊秉绶隶书是清时期伊秉绶的隶书代表作。清隶书代表作，由伊秉绶书写。",
      "highlights": [
        "「伊秉绶隶书」—— 隶书经典之作",
        "「伊秉绶」—— 清著名书法家",
        "「隶书」—— 中国书法五体之一"
      ],
      "full_interpretation": "《伊秉绶隶书》是清时期伊秉绶创作的隶书作品。\n\n清隶书代表作，由伊秉绶书写。\n\n此帖在中国书法史上占有重要地位，是学习隶书的重要范本。",
      "writing_guide": "此隶书古朴厚重，用笔沉稳。临习时注意蚕头燕尾的特点，结构的扁平，以及整体的古朴气质。建议从基本笔画开始，逐步掌握结构规律。"
    },
    "li_020": {
      "title": "金农隶书",
      "author": "金农",
      "dynasty": "清",
      "script_type": "隶书",
      "summary": "清隶书代表作，由金农书写。",
      "background": "金农隶书是清时期金农的隶书代表作。清隶书代表作，由金农书写。",
      "highlights": [
        "「金农隶书」—— 隶书经典之作",
        "「金农」—— 清著名书法家",
        "「隶书」—— 中国书法五体之一"
      ],
      "full_interpretation": "《金农隶书》是清时期金农创作的隶书作品。\n\n清隶书代表作，由金农书写。\n\n此帖在中国书法史上占有重要地位，是学习隶书的重要范本。",
      "writing_guide": "此隶书古朴厚重，用笔沉稳。临习时注意蚕头燕尾的特点，结构的扁平，以及整体的古朴气质。建议从基本笔画开始，逐步掌握结构规律。"
    },
    "zhuan_001": {
      "title": "泰山刻石",
      "author": "李斯（传）",
      "dynasty": "秦",
      "script_type": "篆书",
      "summary": "秦篆书代表作，由李斯（传）书写。",
      "background": "泰山刻石是秦时期李斯（传）的篆书代表作。秦篆书代表作，由李斯（传）书写。",
      "highlights": [
        "「泰山刻石」—— 篆书经典之作",
        "「李斯（传）」—— 秦著名书法家",
        "「篆书」—— 中国书法五体之一"
      ],
      "full_interpretation": "《泰山刻石》是秦时期李斯（传）创作的篆书作品。\n\n秦篆书代表作，由李斯（传）书写。\n\n此帖在中国书法史上占有重要地位，是学习篆书的重要范本。",
      "writing_guide": "此篆书圆润流畅，用笔均匀。临习时注意笔画的圆润，结构的对称，以及整体的古朴气质。建议从基本笔画开始，逐步掌握结构规律。"
    },
    "zhuan_002": {
      "title": "琅琊刻石",
      "author": "李斯（传）",
      "dynasty": "秦",
      "script_type": "篆书",
      "summary": "秦篆书代表作，由李斯（传）书写。",
      "background": "琅琊刻石是秦时期李斯（传）的篆书代表作。秦篆书代表作，由李斯（传）书写。",
      "highlights": [
        "「琅琊刻石」—— 篆书经典之作",
        "「李斯（传）」—— 秦著名书法家",
        "「篆书」—— 中国书法五体之一"
      ],
      "full_interpretation": "《琅琊刻石》是秦时期李斯（传）创作的篆书作品。\n\n秦篆书代表作，由李斯（传）书写。\n\n此帖在中国书法史上占有重要地位，是学习篆书的重要范本。",
      "writing_guide": "此篆书圆润流畅，用笔均匀。临习时注意笔画的圆润，结构的对称，以及整体的古朴气质。建议从基本笔画开始，逐步掌握结构规律。"
    },
    "zhuan_003": {
      "title": "峄山刻石",
      "author": "李斯（传）",
      "dynasty": "秦",
      "script_type": "篆书",
      "summary": "秦篆书代表作，由李斯（传）书写。",
      "background": "峄山刻石是秦时期李斯（传）的篆书代表作。秦篆书代表作，由李斯（传）书写。",
      "highlights": [
        "「峄山刻石」—— 篆书经典之作",
        "「李斯（传）」—— 秦著名书法家",
        "「篆书」—— 中国书法五体之一"
      ],
      "full_interpretation": "《峄山刻石》是秦时期李斯（传）创作的篆书作品。\n\n秦篆书代表作，由李斯（传）书写。\n\n此帖在中国书法史上占有重要地位，是学习篆书的重要范本。",
      "writing_guide": "此篆书圆润流畅，用笔均匀。临习时注意笔画的圆润，结构的对称，以及整体的古朴气质。建议从基本笔画开始，逐步掌握结构规律。"
    },
    "zhuan_004": {
      "title": "会稽刻石",
      "author": "李斯（传）",
      "dynasty": "秦",
      "script_type": "篆书",
      "summary": "秦篆书代表作，由李斯（传）书写。",
      "background": "会稽刻石是秦时期李斯（传）的篆书代表作。秦篆书代表作，由李斯（传）书写。",
      "highlights": [
        "「会稽刻石」—— 篆书经典之作",
        "「李斯（传）」—— 秦著名书法家",
        "「篆书」—— 中国书法五体之一"
      ],
      "full_interpretation": "《会稽刻石》是秦时期李斯（传）创作的篆书作品。\n\n秦篆书代表作，由李斯（传）书写。\n\n此帖在中国书法史上占有重要地位，是学习篆书的重要范本。",
      "writing_guide": "此篆书圆润流畅，用笔均匀。临习时注意笔画的圆润，结构的对称，以及整体的古朴气质。建议从基本笔画开始，逐步掌握结构规律。"
    },
    "zhuan_005": {
      "title": "毛公鼎铭文",
      "author": "不可考",
      "dynasty": "西周",
      "script_type": "篆书",
      "summary": "西周篆书代表作，作者不可考。",
      "background": "毛公鼎铭文是西周时期不可考的篆书代表作。西周篆书代表作，作者不可考。",
      "highlights": [
        "「毛公鼎铭文」—— 篆书经典之作",
        "「不可考」—— 西周著名书法家",
        "「篆书」—— 中国书法五体之一"
      ],
      "full_interpretation": "《毛公鼎铭文》是西周时期不可考创作的篆书作品。\n\n西周篆书代表作，作者不可考。\n\n此帖在中国书法史上占有重要地位，是学习篆书的重要范本。",
      "writing_guide": "此篆书圆润流畅，用笔均匀。临习时注意笔画的圆润，结构的对称，以及整体的古朴气质。建议从基本笔画开始，逐步掌握结构规律。"
    },
    "zhuan_006": {
      "title": "散氏盘铭文",
      "author": "不可考",
      "dynasty": "西周",
      "script_type": "篆书",
      "summary": "西周篆书代表作，作者不可考。",
      "background": "散氏盘铭文是西周时期不可考的篆书代表作。西周篆书代表作，作者不可考。",
      "highlights": [
        "「散氏盘铭文」—— 篆书经典之作",
        "「不可考」—— 西周著名书法家",
        "「篆书」—— 中国书法五体之一"
      ],
      "full_interpretation": "《散氏盘铭文》是西周时期不可考创作的篆书作品。\n\n西周篆书代表作，作者不可考。\n\n此帖在中国书法史上占有重要地位，是学习篆书的重要范本。",
      "writing_guide": "此篆书圆润流畅，用笔均匀。临习时注意笔画的圆润，结构的对称，以及整体的古朴气质。建议从基本笔画开始，逐步掌握结构规律。"
    },
    "zhuan_007": {
      "title": "虢季子白盘铭文",
      "author": "不可考",
      "dynasty": "西周",
      "script_type": "篆书",
      "summary": "西周篆书代表作，作者不可考。",
      "background": "虢季子白盘铭文是西周时期不可考的篆书代表作。西周篆书代表作，作者不可考。",
      "highlights": [
        "「虢季子白盘铭文」—— 篆书经典之作",
        "「不可考」—— 西周著名书法家",
        "「篆书」—— 中国书法五体之一"
      ],
      "full_interpretation": "《虢季子白盘铭文》是西周时期不可考创作的篆书作品。\n\n西周篆书代表作，作者不可考。\n\n此帖在中国书法史上占有重要地位，是学习篆书的重要范本。",
      "writing_guide": "此篆书圆润流畅，用笔均匀。临习时注意笔画的圆润，结构的对称，以及整体的古朴气质。建议从基本笔画开始，逐步掌握结构规律。"
    },
    "zhuan_008": {
      "title": "墙盘铭文",
      "author": "不可考",
      "dynasty": "西周",
      "script_type": "篆书",
      "summary": "西周篆书代表作，作者不可考。",
      "background": "墙盘铭文是西周时期不可考的篆书代表作。西周篆书代表作，作者不可考。",
      "highlights": [
        "「墙盘铭文」—— 篆书经典之作",
        "「不可考」—— 西周著名书法家",
        "「篆书」—— 中国书法五体之一"
      ],
      "full_interpretation": "《墙盘铭文》是西周时期不可考创作的篆书作品。\n\n西周篆书代表作，作者不可考。\n\n此帖在中国书法史上占有重要地位，是学习篆书的重要范本。",
      "writing_guide": "此篆书圆润流畅，用笔均匀。临习时注意笔画的圆润，结构的对称，以及整体的古朴气质。建议从基本笔画开始，逐步掌握结构规律。"
    },
    "zhuan_009": {
      "title": "大盂鼎铭文",
      "author": "不可考",
      "dynasty": "西周",
      "script_type": "篆书",
      "summary": "西周篆书代表作，作者不可考。",
      "background": "大盂鼎铭文是西周时期不可考的篆书代表作。西周篆书代表作，作者不可考。",
      "highlights": [
        "「大盂鼎铭文」—— 篆书经典之作",
        "「不可考」—— 西周著名书法家",
        "「篆书」—— 中国书法五体之一"
      ],
      "full_interpretation": "《大盂鼎铭文》是西周时期不可考创作的篆书作品。\n\n西周篆书代表作，作者不可考。\n\n此帖在中国书法史上占有重要地位，是学习篆书的重要范本。",
      "writing_guide": "此篆书圆润流畅，用笔均匀。临习时注意笔画的圆润，结构的对称，以及整体的古朴气质。建议从基本笔画开始，逐步掌握结构规律。"
    },
    "zhuan_010": {
      "title": "颂鼎铭文",
      "author": "不可考",
      "dynasty": "西周",
      "script_type": "篆书",
      "summary": "西周篆书代表作，作者不可考。",
      "background": "颂鼎铭文是西周时期不可考的篆书代表作。西周篆书代表作，作者不可考。",
      "highlights": [
        "「颂鼎铭文」—— 篆书经典之作",
        "「不可考」—— 西周著名书法家",
        "「篆书」—— 中国书法五体之一"
      ],
      "full_interpretation": "《颂鼎铭文》是西周时期不可考创作的篆书作品。\n\n西周篆书代表作，作者不可考。\n\n此帖在中国书法史上占有重要地位，是学习篆书的重要范本。",
      "writing_guide": "此篆书圆润流畅，用笔均匀。临习时注意笔画的圆润，结构的对称，以及整体的古朴气质。建议从基本笔画开始，逐步掌握结构规律。"
    },
    "zhuan_011": {
      "title": "师望鼎铭文",
      "author": "不可考",
      "dynasty": "西周",
      "script_type": "篆书",
      "summary": "西周篆书代表作，作者不可考。",
      "background": "师望鼎铭文是西周时期不可考的篆书代表作。西周篆书代表作，作者不可考。",
      "highlights": [
        "「师望鼎铭文」—— 篆书经典之作",
        "「不可考」—— 西周著名书法家",
        "「篆书」—— 中国书法五体之一"
      ],
      "full_interpretation": "《师望鼎铭文》是西周时期不可考创作的篆书作品。\n\n西周篆书代表作，作者不可考。\n\n此帖在中国书法史上占有重要地位，是学习篆书的重要范本。",
      "writing_guide": "此篆书圆润流畅，用笔均匀。临习时注意笔画的圆润，结构的对称，以及整体的古朴气质。建议从基本笔画开始，逐步掌握结构规律。"
    },
    "zhuan_012": {
      "title": "毛公歆鼎铭文",
      "author": "不可考",
      "dynasty": "西周",
      "script_type": "篆书",
      "summary": "西周篆书代表作，作者不可考。",
      "background": "毛公歆鼎铭文是西周时期不可考的篆书代表作。西周篆书代表作，作者不可考。",
      "highlights": [
        "「毛公歆鼎铭文」—— 篆书经典之作",
        "「不可考」—— 西周著名书法家",
        "「篆书」—— 中国书法五体之一"
      ],
      "full_interpretation": "《毛公歆鼎铭文》是西周时期不可考创作的篆书作品。\n\n西周篆书代表作，作者不可考。\n\n此帖在中国书法史上占有重要地位，是学习篆书的重要范本。",
      "writing_guide": "此篆书圆润流畅，用笔均匀。临习时注意笔画的圆润，结构的对称，以及整体的古朴气质。建议从基本笔画开始，逐步掌握结构规律。"
    },
    "zhuan_013": {
      "title": "戍嗣子鼎铭文",
      "author": "不可考",
      "dynasty": "商代",
      "script_type": "篆书",
      "summary": "商代篆书代表作，作者不可考。",
      "background": "戍嗣子鼎铭文是商代时期不可考的篆书代表作。商代篆书代表作，作者不可考。",
      "highlights": [
        "「戍嗣子鼎铭文」—— 篆书经典之作",
        "「不可考」—— 商代著名书法家",
        "「篆书」—— 中国书法五体之一"
      ],
      "full_interpretation": "《戍嗣子鼎铭文》是商代时期不可考创作的篆书作品。\n\n商代篆书代表作，作者不可考。\n\n此帖在中国书法史上占有重要地位，是学习篆书的重要范本。",
      "writing_guide": "此篆书圆润流畅，用笔均匀。临习时注意笔画的圆润，结构的对称，以及整体的古朴气质。建议从基本笔画开始，逐步掌握结构规律。"
    },
    "zhuan_014": {
      "title": "利簋铭文",
      "author": "不可考",
      "dynasty": "西周",
      "script_type": "篆书",
      "summary": "西周篆书代表作，作者不可考。",
      "background": "利簋铭文是西周时期不可考的篆书代表作。西周篆书代表作，作者不可考。",
      "highlights": [
        "「利簋铭文」—— 篆书经典之作",
        "「不可考」—— 西周著名书法家",
        "「篆书」—— 中国书法五体之一"
      ],
      "full_interpretation": "《利簋铭文》是西周时期不可考创作的篆书作品。\n\n西周篆书代表作，作者不可考。\n\n此帖在中国书法史上占有重要地位，是学习篆书的重要范本。",
      "writing_guide": "此篆书圆润流畅，用笔均匀。临习时注意笔画的圆润，结构的对称，以及整体的古朴气质。建议从基本笔画开始，逐步掌握结构规律。"
    },
    "zhuan_015": {
      "title": "殷墟甲骨文",
      "author": "不可考",
      "dynasty": "商代",
      "script_type": "篆书",
      "summary": "商代篆书代表作，作者不可考。",
      "background": "殷墟甲骨文是商代时期不可考的篆书代表作。商代篆书代表作，作者不可考。",
      "highlights": [
        "「殷墟甲骨文」—— 篆书经典之作",
        "「不可考」—— 商代著名书法家",
        "「篆书」—— 中国书法五体之一"
      ],
      "full_interpretation": "《殷墟甲骨文》是商代时期不可考创作的篆书作品。\n\n商代篆书代表作，作者不可考。\n\n此帖在中国书法史上占有重要地位，是学习篆书的重要范本。",
      "writing_guide": "此篆书圆润流畅，用笔均匀。临习时注意笔画的圆润，结构的对称，以及整体的古朴气质。建议从基本笔画开始，逐步掌握结构规律。"
    },
    "zhuan_016": {
      "title": "司母戊鼎铭文",
      "author": "不可考",
      "dynasty": "商代",
      "script_type": "篆书",
      "summary": "商代篆书代表作，作者不可考。",
      "background": "司母戊鼎铭文是商代时期不可考的篆书代表作。商代篆书代表作，作者不可考。",
      "highlights": [
        "「司母戊鼎铭文」—— 篆书经典之作",
        "「不可考」—— 商代著名书法家",
        "「篆书」—— 中国书法五体之一"
      ],
      "full_interpretation": "《司母戊鼎铭文》是商代时期不可考创作的篆书作品。\n\n商代篆书代表作，作者不可考。\n\n此帖在中国书法史上占有重要地位，是学习篆书的重要范本。",
      "writing_guide": "此篆书圆润流畅，用笔均匀。临习时注意笔画的圆润，结构的对称，以及整体的古朴气质。建议从基本笔画开始，逐步掌握结构规律。"
    },
    "zhuan_017": {
      "title": "四祀邲其卣铭文",
      "author": "不可考",
      "dynasty": "商代",
      "script_type": "篆书",
      "summary": "商代篆书代表作，作者不可考。",
      "background": "四祀邲其卣铭文是商代时期不可考的篆书代表作。商代篆书代表作，作者不可考。",
      "highlights": [
        "「四祀邲其卣铭文」—— 篆书经典之作",
        "「不可考」—— 商代著名书法家",
        "「篆书」—— 中国书法五体之一"
      ],
      "full_interpretation": "《四祀邲其卣铭文》是商代时期不可考创作的篆书作品。\n\n商代篆书代表作，作者不可考。\n\n此帖在中国书法史上占有重要地位，是学习篆书的重要范本。",
      "writing_guide": "此篆书圆润流畅，用笔均匀。临习时注意笔画的圆润，结构的对称，以及整体的古朴气质。建议从基本笔画开始，逐步掌握结构规律。"
    },
    "zhuan_018": {
      "title": "石鼓文",
      "author": "不可考",
      "dynasty": "春秋/战国",
      "script_type": "篆书",
      "summary": "春秋/战国篆书代表作，作者不可考。",
      "background": "石鼓文是春秋/战国时期不可考的篆书代表作。春秋/战国篆书代表作，作者不可考。",
      "highlights": [
        "「石鼓文」—— 篆书经典之作",
        "「不可考」—— 春秋/战国著名书法家",
        "「篆书」—— 中国书法五体之一"
      ],
      "full_interpretation": "《石鼓文》是春秋/战国时期不可考创作的篆书作品。\n\n春秋/战国篆书代表作，作者不可考。\n\n此帖在中国书法史上占有重要地位，是学习篆书的重要范本。",
      "writing_guide": "此篆书圆润流畅，用笔均匀。临习时注意笔画的圆润，结构的对称，以及整体的古朴气质。建议从基本笔画开始，逐步掌握结构规律。"
    },
    "zhuan_019": {
      "title": "邓石如篆书",
      "author": "邓石如",
      "dynasty": "清",
      "script_type": "篆书",
      "summary": "清篆书代表作，由邓石如书写。",
      "background": "邓石如篆书是清时期邓石如的篆书代表作。清篆书代表作，由邓石如书写。",
      "highlights": [
        "「邓石如篆书」—— 篆书经典之作",
        "「邓石如」—— 清著名书法家",
        "「篆书」—— 中国书法五体之一"
      ],
      "full_interpretation": "《邓石如篆书》是清时期邓石如创作的篆书作品。\n\n清篆书代表作，由邓石如书写。\n\n此帖在中国书法史上占有重要地位，是学习篆书的重要范本。",
      "writing_guide": "此篆书圆润流畅，用笔均匀。临习时注意笔画的圆润，结构的对称，以及整体的古朴气质。建议从基本笔画开始，逐步掌握结构规律。"
    },
    "zhuan_020": {
      "title": "吴昌硕篆书",
      "author": "吴昌硕",
      "dynasty": "清末民初",
      "script_type": "篆书",
      "summary": "清末民初篆书代表作，由吴昌硕书写。",
      "background": "吴昌硕篆书是清末民初时期吴昌硕的篆书代表作。清末民初篆书代表作，由吴昌硕书写。",
      "highlights": [
        "「吴昌硕篆书」—— 篆书经典之作",
        "「吴昌硕」—— 清末民初著名书法家",
        "「篆书」—— 中国书法五体之一"
      ],
      "full_interpretation": "《吴昌硕篆书》是清末民初时期吴昌硕创作的篆书作品。\n\n清末民初篆书代表作，由吴昌硕书写。\n\n此帖在中国书法史上占有重要地位，是学习篆书的重要范本。",
      "writing_guide": "此篆书圆润流畅，用笔均匀。临习时注意笔画的圆润，结构的对称，以及整体的古朴气质。建议从基本笔画开始，逐步掌握结构规律。"
    },
    "xing_001": {
      "title": "兰亭序",
      "author": "王羲之",
      "dynasty": "东晋",
      "script_type": "行书",
      "summary": "行书第一，飘若浮云、矫若惊龙。",
      "background": "东晋穆帝永和九年（353 年）三月三日，王羲之与谢安、孙绰等四十一位军政高官，在山阴（今浙江绍兴）兰亭「修禊」，会上各人作诗，王羲之为他们的诗写的序文手稿。《兰亭序》中记叙兰亭周围山水之美和聚会的欢乐之情，抒发作者对于生死无常的感慨。",
      "highlights": [
        "「群贤毕至，少长咸集」—— 形容人才济济，老少齐聚的盛况",
        "「仰观宇宙之大，俯察品类之盛」—— 表达观察天地万物的开阔胸襟",
        "「死生亦大矣」—— 对生命本质的深刻思考"
      ],
      "full_interpretation": "【第一段】\n永和九年，岁在癸丑，暮春之初——永和九年（公元 353 年），正值癸丑年，暮春三月初。\n会于会稽山阴之兰亭，修禊事也——我们会集在会稽郡山阴县的兰亭，举行修禊活动。\n群贤毕至，少长咸集——众多贤才都到了，年老年少的都聚集在一起。\n\n【第二段】\n此地有崇山峻岭，茂林修竹——这里有高峻的山岭，茂密的树林和修长的竹子。\n又有清流激湍，映带左右——又有清澈湍急的溪流，环绕在亭子左右。\n引以为流觞曲水，列坐其次——我们引溪水作为流觞的曲水，大家依次坐在水边。\n虽无丝竹管弦之盛，一觞一咏，亦足以畅叙幽情——虽然没有管弦音乐的盛况，但一边饮酒一边赋诗，也足以畅快地表达幽雅的情怀。\n\n【第三段】\n是日也，天朗气清，惠风和畅——这一天，天空晴朗，空气清新，和风温暖舒畅。\n仰观宇宙之大，俯察品类之盛——抬头观看宇宙的广大，低头审视万物的繁盛。\n所以游目骋怀，足以极视听之娱，信可乐也——借此纵目观览，舒展胸怀，足以尽享视听的乐趣，实在是快乐啊。\n\n【第四段】\n夫人之相与，俯仰一世——人们相互交往，很快便度过一生。\n或取诸怀抱，悟言一室之内——有的人在室内与朋友畅谈抱负。\n或因寄所托，放浪形骸之外——有的人寄托情怀于外物，不受礼法约束。\n\n【第五段】\n虽趣舍万殊，静躁不同——虽然人们的取舍千差万别，性情安静与浮躁也不同。\n当其欣于所遇，暂得于己，怏然自足，不知老之将至——但当他们对所接触的事物感到高兴时，暂时得意，快乐自足，竟不知道衰老即将到来。\n\n【第六段】\n及其所之既倦，情随事迁，感慨系之矣——等到对所得到的东西已经厌倦，感情随着事物的变化而改变，感慨便随之产生。\n向之所欣，俯仰之间，已为陈迹——过去所喜欢的东西，转眼间已成为旧迹。\n犹不能不以之兴怀——尚且不能不因此引发感慨。\n况修短随化，终期于尽——何况寿命长短听凭造化，最终都要归于消亡。\n\n【第七段】\n古人云：「死生亦大矣。」岂不痛哉——古人说：「死生也是件大事啊。」怎能不悲痛呢！\n每览昔人兴感之由，若合一契——每当看到古人引发感慨的原因，像符契那样相合。\n未尝不临文嗟悼，不能喻之于怀——没有不对着文章叹息哀伤的，心里却不明白为什么会这样。\n\n【第八段】\n固知一死生为虚诞，齐彭殇为妄作——本来知道把死和生等同起来的说法是虚妄的，把长寿和短命等同起来的说法是荒诞的。\n后之视今，亦犹今之视昔——后人看待今天，也像今天看待从前一样。\n悲夫——真是可悲啊！\n\n【第九段】\n故列叙时人，录其所述——所以我一一记下当时与会的人，录下他们所作的诗篇。\n虽世殊事异，所以兴怀，其致一也——纵使时代变了，世事不同了，但触发人们情怀的原因，他们的思想情趣是一样的。\n后之览者，亦将有感于斯文——后世的读者，也将对这次集会的诗文有所感慨。",
      "writing_guide": "此行书流畅自然，用笔灵动。临习时注意笔画的连贯性，结构的疏密对比，以及整体的飘逸气质。建议先掌握基本笔法，再追求气韵生动。"
    },
    "xing_002": {
      "title": "祭侄文稿",
      "author": "颜真卿",
      "dynasty": "唐",
      "script_type": "行书",
      "summary": "壮烈之美，情真笔亦真。",
      "background": "唐肃宗乾元元年（758 年），颜真卿为祭奠在安史之乱中牺牲的侄子颜季明所作。颜杲卿（颜真卿堂兄）和颜季明父子在常山抗击叛军，城破后壮烈殉国。颜真卿得知消息后，悲痛欲绝，挥泪写下这篇祭文。",
      "highlights": [
        "「父陷子死，巢倾卵覆」—— 形容全家殉国的惨烈",
        "「呜呼哀哉」—— 反复出现的悲叹，表达极度悲痛",
        "「百身何赎」—— 表达无法挽回亲人生命的无奈"
      ],
      "full_interpretation": "【开头】\n维乾元元年，岁次戊戌，九月庚午朔，三日壬申——时在乾元元年（公元 758 年），岁次戊戌，九月初一庚午日，初三壬申日。\n\n【自我介绍】\n第十三叔、银青光禄大夫、使持节蒲州诸军事、蒲州刺史、上轻车都尉、丹阳县开国侯真卿——第十三叔父、银青光禄大夫、持节蒲州诸军事、蒲州刺史、上轻车都尉、丹阳县开国侯颜真卿。\n以清酌庶羞，祭于亡侄赠赞善大夫季明之灵——以清酒和各种祭品，祭奠亡侄追赠赞善大夫季明的英灵。\n\n【追忆侄子】\n惟尔挺生，夙标幼德——想你天生出众，从小就显示出高尚的品德。\n宗庙瑚琏，阶庭兰玉——你是宗庙中的瑚琏重器，庭院中的兰玉佳木。\n每慰人心，方期戬谷——常常安慰人心，正期望你能获得福禄。\n\n【安史之乱】\n何图逆贼闲衅，称兵犯顺——哪里想到逆贼安禄山挑起事端，举兵犯上作乱。\n尔父竭诚，常山作郡——你的父亲颜杲卿竭诚尽忠，在常山郡做太守。\n余时受命，亦在平原——我当时受命，也在平原郡。\n仁兄爱我，俾尔传言——仁爱的兄长爱护我，让你来传递消息。\n尔既归止，爰开土门——你回去之后，就打开了土门关。\n土门既开，凶威大蹙——土门打开后，叛贼的凶威大受挫折。\n\n【城破殉国】\n贼臣不救，孤城围逼——贼臣拥兵不救，孤城被围困逼迫。\n父陷子死，巢倾卵覆——父亲被俘，儿子战死，巢穴倾覆，鸟卵破碎。\n天不悔祸，谁为荼毒——上天不悔恨降下灾祸，谁来阻止这荼毒？\n念尔遘残，百身何赎——想到你遭遇残害，即使百死也无法赎回。\n呜呼哀哉——唉，真是悲哀啊！\n\n【收殓遗骨】\n吾承天泽，移牧河关——我承蒙皇恩，调任河关一带。\n泉明比者，再陷常山——泉明等人，再次攻陷常山。\n携尔首榇，及兹同还——带着你的灵柩，到这里一同返回。\n抚念摧切，震悼心颜——抚念之下，悲痛欲绝，震惊哀悼，心如刀割。\n\n【结尾】\n方俟远日，卜尔幽宅——正等待吉日，为你选择安息之地。\n魂而有知，无嗟久客——你的英灵如果有知，不要叹息长久客居他乡。\n呜呼哀哉！尚飨——唉，真是悲哀啊！请享用祭品吧！",
      "writing_guide": "此行书流畅自然，用笔灵动。临习时注意笔画的连贯性，结构的疏密对比，以及整体的飘逸气质。建议先掌握基本笔法，再追求气韵生动。"
    },
    "xing_003": {
      "title": "黄州寒食帖",
      "author": "苏轼",
      "dynasty": "北宋",
      "script_type": "行书",
      "summary": "文人之心，笔里有风雨。",
      "background": "北宋元丰五年（1082 年），苏轼被贬黄州的第三年寒食节所作。此时苏轼因「乌台诗案」被贬黄州已三年，生活困顿，心情抑郁。两首诗表达了作者身处逆境中的苦闷和对故乡的思念。",
      "highlights": [
        "「小屋如渔舟，濛濛水云里」—— 描写居所简陋，如渔船漂泊",
        "「君门深九重，坟墓在万里」—— 表达思君念祖之情",
        "「死灰吹不起」—— 形容心灰意冷的绝望心境"
      ],
      "full_interpretation": "【第一首】\n自我来黄州，已过三寒食——自从我来到黄州，已经过了三个寒食节。\n年年欲惜春，春去不容惜——每年都想要珍惜春天，但春天离去不容挽留。\n今年又苦雨，两月秋萧瑟——今年又遇上连绵苦雨，两个月来如同秋天般萧瑟。\n卧闻海棠花，泥污燕支雪——躺在床上听到海棠花落，花瓣被泥水玷污，如同胭脂雪被弄脏。\n闇中偷负去，夜半真有力——黑暗中偷偷被带走，夜半时分真有力量在推动。\n何殊病少年，病起头已白——这与患病的少年有何不同，病好之后头发已经白了。\n\n【第二首】\n春江欲入户，雨势来不已——春天的江水仿佛要涌入家门，雨势连绵不断。\n小屋如渔舟，濛濛水云里——小小的屋子像渔船一样，在濛濛水云中飘荡。\n空庖煮寒菜，破灶烧湿苇——空荡的厨房里煮着寒酸的野菜，破旧的灶台烧着潮湿的芦苇。\n那知是寒食，但见乌衔纸——哪里知道今天是寒食节，只看见乌鸦衔着纸钱。\n君门深九重，坟墓在万里——君王的家门深达九重，祖先的坟墓远在万里之外。\n也拟哭途穷，死灰吹不起——也想学阮籍哭于途穷，但心如死灰，连吹都吹不起来了。",
      "writing_guide": "此行书流畅自然，用笔灵动。临习时注意笔画的连贯性，结构的疏密对比，以及整体的飘逸气质。建议先掌握基本笔法，再追求气韵生动。"
    },
    "xing_004": {
      "title": "集字圣教序",
      "author": "怀仁（集王羲之书）",
      "dynasty": "唐",
      "script_type": "行书",
      "summary": "典雅极致，唐代集字之极则。",
      "background": "集字圣教序是唐时期怀仁（集王羲之书）的行书代表作。典雅极致，唐代集字之极则。",
      "highlights": [
        "「集字圣教序」—— 行书经典之作",
        "「怀仁（集王羲之书）」—— 唐著名书法家",
        "「行书」—— 中国书法五体之一"
      ],
      "full_interpretation": "《集字圣教序》是唐时期怀仁（集王羲之书）创作的行书作品。\n\n典雅极致，唐代集字之极则。\n\n此帖在中国书法史上占有重要地位，是学习行书的重要范本。",
      "writing_guide": "此行书流畅自然，用笔灵动。临习时注意笔画的连贯性，结构的疏密对比，以及整体的飘逸气质。建议先掌握基本笔法，再追求气韵生动。"
    },
    "xing_005": {
      "title": "蜀素帖",
      "author": "米芾",
      "dynasty": "北宋",
      "script_type": "行书",
      "summary": "风樯阵马，米芾行书巅峰。",
      "background": "蜀素帖是北宋时期米芾的行书代表作。风樯阵马，米芾行书巅峰。",
      "highlights": [
        "「蜀素帖」—— 行书经典之作",
        "「米芾」—— 北宋著名书法家",
        "「行书」—— 中国书法五体之一"
      ],
      "full_interpretation": "《蜀素帖》是北宋时期米芾创作的行书作品。\n\n风樯阵马，米芾行书巅峰。\n\n此帖在中国书法史上占有重要地位，是学习行书的重要范本。",
      "writing_guide": "此行书流畅自然，用笔灵动。临习时注意笔画的连贯性，结构的疏密对比，以及整体的飘逸气质。建议先掌握基本笔法，再追求气韵生动。"
    },
    "xing_006": {
      "title": "松风阁诗",
      "author": "黄庭坚",
      "dynasty": "北宋",
      "script_type": "行书",
      "summary": "老干发青，骨力苍劲。",
      "background": "松风阁诗是北宋时期黄庭坚的行书代表作。老干发青，骨力苍劲。",
      "highlights": [
        "「松风阁诗」—— 行书经典之作",
        "「黄庭坚」—— 北宋著名书法家",
        "「行书」—— 中国书法五体之一"
      ],
      "full_interpretation": "《松风阁诗》是北宋时期黄庭坚创作的行书作品。\n\n老干发青，骨力苍劲。\n\n此帖在中国书法史上占有重要地位，是学习行书的重要范本。",
      "writing_guide": "此行书流畅自然，用笔灵动。临习时注意笔画的连贯性，结构的疏密对比，以及整体的飘逸气质。建议先掌握基本笔法，再追求气韵生动。"
    },
    "xing_007": {
      "title": "韭花帖",
      "author": "杨凝式",
      "dynasty": "五代",
      "script_type": "行书",
      "summary": "清逸淡远，尺牍之雅。",
      "background": "韭花帖是五代时期杨凝式的行书代表作。清逸淡远，尺牍之雅。",
      "highlights": [
        "「韭花帖」—— 行书经典之作",
        "「杨凝式」—— 五代著名书法家",
        "「行书」—— 中国书法五体之一"
      ],
      "full_interpretation": "《韭花帖》是五代时期杨凝式创作的行书作品。\n\n清逸淡远，尺牍之雅。\n\n此帖在中国书法史上占有重要地位，是学习行书的重要范本。",
      "writing_guide": "此行书流畅自然，用笔灵动。临习时注意笔画的连贯性，结构的疏密对比，以及整体的飘逸气质。建议先掌握基本笔法，再追求气韵生动。"
    },
    "xing_008": {
      "title": "伯远帖",
      "author": "王珣",
      "dynasty": "东晋",
      "script_type": "行书",
      "summary": "纯粹晋美，清雅不俗。",
      "background": "伯远帖是东晋时期王珣的行书代表作。纯粹晋美，清雅不俗。",
      "highlights": [
        "「伯远帖」—— 行书经典之作",
        "「王珣」—— 东晋著名书法家",
        "「行书」—— 中国书法五体之一"
      ],
      "full_interpretation": "《伯远帖》是东晋时期王珣创作的行书作品。\n\n纯粹晋美，清雅不俗。\n\n此帖在中国书法史上占有重要地位，是学习行书的重要范本。",
      "writing_guide": "此行书流畅自然，用笔灵动。临习时注意笔画的连贯性，结构的疏密对比，以及整体的飘逸气质。建议先掌握基本笔法，再追求气韵生动。"
    },
    "xing_009": {
      "title": "土母帖",
      "author": "李建中",
      "dynasty": "北宋",
      "script_type": "行书",
      "summary": "淳朴自然，近人可学。",
      "background": "土母帖是北宋时期李建中的行书代表作。淳朴自然，近人可学。",
      "highlights": [
        "「土母帖」—— 行书经典之作",
        "「李建中」—— 北宋著名书法家",
        "「行书」—— 中国书法五体之一"
      ],
      "full_interpretation": "《土母帖》是北宋时期李建中创作的行书作品。\n\n淳朴自然，近人可学。\n\n此帖在中国书法史上占有重要地位，是学习行书的重要范本。",
      "writing_guide": "此行书流畅自然，用笔灵动。临习时注意笔画的连贯性，结构的疏密对比，以及整体的飘逸气质。建议先掌握基本笔法，再追求气韵生动。"
    },
    "xing_010": {
      "title": "洛神赋",
      "author": "赵孟頫",
      "dynasty": "元",
      "script_type": "行书",
      "summary": "华丽典雅，赵体之范。",
      "background": "洛神赋是元时期赵孟頫的行书代表作。华丽典雅，赵体之范。",
      "highlights": [
        "「洛神赋」—— 行书经典之作",
        "「赵孟頫」—— 元著名书法家",
        "「行书」—— 中国书法五体之一"
      ],
      "full_interpretation": "《洛神赋》是元时期赵孟頫创作的行书作品。\n\n华丽典雅，赵体之范。\n\n此帖在中国书法史上占有重要地位，是学习行书的重要范本。",
      "writing_guide": "此行书流畅自然，用笔灵动。临习时注意笔画的连贯性，结构的疏密对比，以及整体的飘逸气质。建议先掌握基本笔法，再追求气韵生动。"
    },
    "xing_011": {
      "title": "苕溪诗帖",
      "author": "米芾",
      "dynasty": "北宋",
      "script_type": "行书",
      "summary": "神采奕奕，行气纵横。",
      "background": "苕溪诗帖是北宋时期米芾的行书代表作。神采奕奕，行气纵横。",
      "highlights": [
        "「苕溪诗帖」—— 行书经典之作",
        "「米芾」—— 北宋著名书法家",
        "「行书」—— 中国书法五体之一"
      ],
      "full_interpretation": "《苕溪诗帖》是北宋时期米芾创作的行书作品。\n\n神采奕奕，行气纵横。\n\n此帖在中国书法史上占有重要地位，是学习行书的重要范本。",
      "writing_guide": "此行书流畅自然，用笔灵动。临习时注意笔画的连贯性，结构的疏密对比，以及整体的飘逸气质。建议先掌握基本笔法，再追求气韵生动。"
    },
    "xing_012": {
      "title": "平复帖",
      "author": "陆机",
      "dynasty": "西晋",
      "script_type": "草书",
      "summary": "苍茫神妙，章草与行意相接。",
      "background": "平复帖是西晋时期陆机的草书代表作。苍茫神妙，章草与行意相接。",
      "highlights": [
        "「平复帖」—— 草书经典之作",
        "「陆机」—— 西晋著名书法家",
        "「草书」—— 中国书法五体之一"
      ],
      "full_interpretation": "《平复帖》是西晋时期陆机创作的草书作品。\n\n苍茫神妙，章草与行意相接。\n\n此帖在中国书法史上占有重要地位，是学习草书的重要范本。",
      "writing_guide": "此草书奔放豪迈，用笔迅疾。临习时注意笔画的连贯性，结构的变化，以及整体的气势。建议先掌握草法，再追求神韵。"
    },
    "xing_013": {
      "title": "中秋帖",
      "author": "王献之（传）",
      "dynasty": "东晋",
      "script_type": "行书",
      "summary": "奔腾跳跃，行草之神。",
      "background": "中秋帖是东晋时期王献之（传）的行书代表作。奔腾跳跃，行草之神。",
      "highlights": [
        "「中秋帖」—— 行书经典之作",
        "「王献之（传）」—— 东晋著名书法家",
        "「行书」—— 中国书法五体之一"
      ],
      "full_interpretation": "《中秋帖》是东晋时期王献之（传）创作的行书作品。\n\n奔腾跳跃，行草之神。\n\n此帖在中国书法史上占有重要地位，是学习行书的重要范本。",
      "writing_guide": "此行书流畅自然，用笔灵动。临习时注意笔画的连贯性，结构的疏密对比，以及整体的飘逸气质。建议先掌握基本笔法，再追求气韵生动。"
    },
    "cao_001": {
      "title": "书谱",
      "author": "孙过庭",
      "dynasty": "唐",
      "script_type": "草书",
      "summary": "智巧兼优，论书与草法并传。",
      "background": "书谱是唐时期孙过庭的草书代表作。智巧兼优，论书与草法并传。",
      "highlights": [
        "「书谱」—— 草书经典之作",
        "「孙过庭」—— 唐著名书法家",
        "「草书」—— 中国书法五体之一"
      ],
      "full_interpretation": "《书谱》是唐时期孙过庭创作的草书作品。\n\n智巧兼优，论书与草法并传。\n\n此帖在中国书法史上占有重要地位，是学习草书的重要范本。",
      "writing_guide": "此草书奔放豪迈，用笔迅疾。临习时注意笔画的连贯性，结构的变化，以及整体的气势。建议先掌握草法，再追求神韵。"
    },
    "cao_002": {
      "title": "自叙帖",
      "author": "怀素",
      "dynasty": "唐",
      "script_type": "草书",
      "summary": "骤雨旋风，狂草长卷代表作。",
      "background": "自叙帖是唐时期怀素的草书代表作。骤雨旋风，狂草长卷代表作。",
      "highlights": [
        "「自叙帖」—— 草书经典之作",
        "「怀素」—— 唐著名书法家",
        "「草书」—— 中国书法五体之一"
      ],
      "full_interpretation": "《自叙帖》是唐时期怀素创作的草书作品。\n\n骤雨旋风，狂草长卷代表作。\n\n此帖在中国书法史上占有重要地位，是学习草书的重要范本。",
      "writing_guide": "此草书奔放豪迈，用笔迅疾。临习时注意笔画的连贯性，结构的变化，以及整体的气势。建议先掌握草法，再追求神韵。"
    },
    "cao_003": {
      "title": "十七帖",
      "author": "王羲之",
      "dynasty": "东晋",
      "script_type": "草书",
      "summary": "雅致纯粹，草书刻帖之祖。",
      "background": "十七帖是东晋时期王羲之的草书代表作。雅致纯粹，草书刻帖之祖。",
      "highlights": [
        "「十七帖」—— 草书经典之作",
        "「王羲之」—— 东晋著名书法家",
        "「草书」—— 中国书法五体之一"
      ],
      "full_interpretation": "《十七帖》是东晋时期王羲之创作的草书作品。\n\n雅致纯粹，草书刻帖之祖。\n\n此帖在中国书法史上占有重要地位，是学习草书的重要范本。",
      "writing_guide": "此草书奔放豪迈，用笔迅疾。临习时注意笔画的连贯性，结构的变化，以及整体的气势。建议先掌握草法，再追求神韵。"
    },
    "cao_004": {
      "title": "古诗四帖",
      "author": "张旭",
      "dynasty": "唐",
      "script_type": "草书",
      "summary": "颠狂之境，狂草巅峰。",
      "background": "古诗四帖是唐时期张旭的草书代表作。颠狂之境，狂草巅峰。",
      "highlights": [
        "「古诗四帖」—— 草书经典之作",
        "「张旭」—— 唐著名书法家",
        "「草书」—— 中国书法五体之一"
      ],
      "full_interpretation": "《古诗四帖》是唐时期张旭创作的草书作品。\n\n颠狂之境，狂草巅峰。\n\n此帖在中国书法史上占有重要地位，是学习草书的重要范本。",
      "writing_guide": "此草书奔放豪迈，用笔迅疾。临习时注意笔画的连贯性，结构的变化，以及整体的气势。建议先掌握草法，再追求神韵。"
    },
    "cao_005": {
      "title": "肚痛帖",
      "author": "张旭",
      "dynasty": "唐",
      "script_type": "草书",
      "summary": "神鬼莫测，一气呵成。",
      "background": "肚痛帖是唐时期张旭的草书代表作。神鬼莫测，一气呵成。",
      "highlights": [
        "「肚痛帖」—— 草书经典之作",
        "「张旭」—— 唐著名书法家",
        "「草书」—— 中国书法五体之一"
      ],
      "full_interpretation": "《肚痛帖》是唐时期张旭创作的草书作品。\n\n神鬼莫测，一气呵成。\n\n此帖在中国书法史上占有重要地位，是学习草书的重要范本。",
      "writing_guide": "此草书奔放豪迈，用笔迅疾。临习时注意笔画的连贯性，结构的变化，以及整体的气势。建议先掌握草法，再追求神韵。"
    },
    "cao_006": {
      "title": "苦笋帖",
      "author": "怀素",
      "dynasty": "唐",
      "script_type": "草书",
      "summary": "清俊散淡，尺牍见真章。",
      "background": "苦笋帖是唐时期怀素的草书代表作。清俊散淡，尺牍见真章。",
      "highlights": [
        "「苦笋帖」—— 草书经典之作",
        "「怀素」—— 唐著名书法家",
        "「草书」—— 中国书法五体之一"
      ],
      "full_interpretation": "《苦笋帖》是唐时期怀素创作的草书作品。\n\n清俊散淡，尺牍见真章。\n\n此帖在中国书法史上占有重要地位，是学习草书的重要范本。",
      "writing_guide": "此草书奔放豪迈，用笔迅疾。临习时注意笔画的连贯性，结构的变化，以及整体的气势。建议先掌握草法，再追求神韵。"
    },
    "cao_007": {
      "title": "初月帖",
      "author": "王羲之",
      "dynasty": "东晋",
      "script_type": "草书",
      "summary": "神采焕发，晋人风神在此。",
      "background": "初月帖是东晋时期王羲之的草书代表作。神采焕发，晋人风神在此。",
      "highlights": [
        "「初月帖」—— 草书经典之作",
        "「王羲之」—— 东晋著名书法家",
        "「草书」—— 中国书法五体之一"
      ],
      "full_interpretation": "《初月帖》是东晋时期王羲之创作的草书作品。\n\n神采焕发，晋人风神在此。\n\n此帖在中国书法史上占有重要地位，是学习草书的重要范本。",
      "writing_guide": "此草书奔放豪迈，用笔迅疾。临习时注意笔画的连贯性，结构的变化，以及整体的气势。建议先掌握草法，再追求神韵。"
    },
    "zhe_001": {
      "title": "天发神谶碑",
      "author": "不可考",
      "dynasty": "三国/吴",
      "script_type": "隶书",
      "summary": "奇诡壮美，以隶法写篆意。",
      "background": "天发神谶碑是三国/吴时期不可考的隶书代表作。奇诡壮美，以隶法写篆意。",
      "highlights": [
        "「天发神谶碑」—— 隶书经典之作",
        "「不可考」—— 三国/吴著名书法家",
        "「隶书」—— 中国书法五体之一"
      ],
      "full_interpretation": "《天发神谶碑》是三国/吴时期不可考创作的隶书作品。\n\n奇诡壮美，以隶法写篆意。\n\n此帖在中国书法史上占有重要地位，是学习隶书的重要范本。",
      "writing_guide": "此隶书古朴厚重，用笔沉稳。临习时注意蚕头燕尾的特点，结构的扁平，以及整体的古朴气质。建议从基本笔画开始，逐步掌握结构规律。"
    }
  }
}